{
  "users": [
    {
      "id": 1,
      "name": "Herman Munson",
      "email": "herm@adamshouse.com"
    },
    {
      "id": 2,
      "name": "Lily Munson",
      "email": "lily@adamshouse"
    },
    {
      "name": "John Smith",
      "email": "smith@aol.com",
      "id": 3
    },
    {
      "name": "Lily Munson",
      "email": "smith@aol.com",
      "id": 4
    },
    {
      "name": "Drew is a Dumbass",
      "email": "idiotsRUS@helpme.com",
      "id": 5
    },
    {
      "name": "Slinky Wierdo",
      "email": "shady@aol.com",
      "id": 6
    },
    {
      "name": "Roger Sterling",
      "email": "blah@john.com",
      "id": 7
    },
    {
      "name": "Jeff Holmes",
      "email": "nashville@pessimist.com",
      "id": 8
    },
    {
      "name": "",
      "email": "",
      "id": 9
    },
    {
      "name": "zzzzzzz",
      "email": "zzzzzzz",
      "id": 10
    },
    {
      "name": "taco",
      "email": "fever@mexican.com",
      "id": 11
    },
    {
      "name": "Mel",
      "email": "madealogin@heckyeah.com",
      "id": 11
    },
    {
      "name": "afafwefwefwef2",
      "email": "23r2ewfsdsfdsdfdfd",
      "id": 12
    }
  ],
  "friends": [
    {
      "id": 1,
      "users_id": 1,
      "users_id_fk": 2
    }
  ],
  "events": [
    {
      "id": 1,
      "title": "Party at the Moon Tower",
      "date": "now",
      "time": "now",
      "location": "Moon Tower"
    }
  ],
  "news": [
    {
      "id": 1,
      "url": "https://www.imdb.com/title/tt0387808/",
      "title": "End of the World",
      "synopsis": "Pestilence, War, Famine, Death"
    }
  ],
  "tasks": [
    {
      "task": "Test Task 1",
      "date": "2019-07-03",
      "userId": "1",
      "id": 1
    },
    {
      "task": "Test Task 2",
      "date": "2019-07-03",
      "userId": "1",
      "id": 2
    },
    {
      "task": "Test Task 3",
      "date": "2019-07-03",
      "userId": "1",
      "id": 3
    },
    {
      "task": "Test Task 4",
      "date": "2019-07-03",
      "userId": "1",
      "id": 4
    },
    {
      "task": "test task 5",
      "date": "2019-07-03",
      "userId": "1",
      "id": 5
    },
    {
      "task": "new task from mo",
      "date": "2019-07-10",
      "userId": "1",
      "id": 6
    },
    {
      "task": "test task 7",
      "date": "2019-07-03",
      "userId": "1",
      "id": 7
    },
    {
      "task": "task 9",
      "date": "2019-07-03",
      "userId": "1",
      "id": 8
    },
    {
      "task": "task 10",
      "date": "2019-07-03",
      "userId": "1",
      "id": 9
    },
    {
      "task": "task 15",
      "date": "2019-07-03",
      "userId": "1",
      "id": 10
    },
    {
      "task": "task 17",
      "date": "2019-07-03",
      "userId": "1",
      "id": 11
    }
  ]
}